bSuite/utils/__init__.py
bSuite/utils/spotify.py
bSuite/utils/storage.py
bSuite/utils/strings.py
bSuite/utils/time.py
bSuite_utils-1.1.0.dist-info/LICENSE
bSuite_utils-1.1.0.dist-info/METADATA
bSuite_utils-1.1.0.dist-info/WHEEL
bSuite_utils-1.1.0.dist-info/top_level.txt
bSuite_utils-1.1.0.dist-info/RECORD
