Metadata-Version: 2.1
Name: bSuite-utils
Version: 1.1.0
Summary: misc utils submodule of bSuite
Author-email: John Birdwell <j.c.birdwell@gmail.com>
License: GNU GENERAL PUBLIC LICENSE
Requires-Python: >=3.11
License-File: LICENSE
